rpi_hardware_pwm/__init__.py
rpi_hardware_pwm/py.typed
rpi_hardware_pwm-0.2.1.dist-info/LICENSE
rpi_hardware_pwm-0.2.1.dist-info/METADATA
rpi_hardware_pwm-0.2.1.dist-info/WHEEL
rpi_hardware_pwm-0.2.1.dist-info/top_level.txt
rpi_hardware_pwm-0.2.1.dist-info/RECORD
