Metadata-Version: 2.1
Name: rpi_hardware_pwm
Version: 0.2.1
Summary: Control Hardware PWM on the Raspberry Pi
Home-page: https://github.com/Pioreactor/rpi_hardware_pwm
Author: Cam Davidson-Pilon
Author-email: cam@pioreactor.com
License: OSI Approved :: GNU General Public License v3 (GPLv3)
Keywords: raspberry pi,pwm,hardware
Classifier: Development Status :: 4 - Beta
Classifier: Topic :: System :: Hardware
Requires-Python: >=3.5
License-File: LICENSE
